journalizeio/__init__.py
journalizeio/client.py
journalizeio-0.0.4.dist-info/LICENSE
journalizeio-0.0.4.dist-info/METADATA
journalizeio-0.0.4.dist-info/WHEEL
journalizeio-0.0.4.dist-info/top_level.txt
journalizeio-0.0.4.dist-info/RECORD
