Metadata-Version: 2.1
Name: journalizeio
Version: 0.0.4
Summary: Client library for journalize.io
Home-page: https://github.com/journalize-io/journalize-python
Author: Journalize.io
Author-email: support@journalize.io
Project-URL: Homepage, https://www.journalize.io
Project-URL: Source Code, https://github.com/journalize-io/journalize-python
Requires-Python: >=3.6
License-File: LICENSE
Requires-Dist: requests
